poppy/__init__.py
poppy/history.py
poppy/plot.py
poppy/poppy.py
poppy/samples.py
poppy/transforms.py
poppy/utils.py
poppy/flows/__init__.py
poppy/flows/base.py
poppy/flows/jax/__init__.py
poppy/flows/jax/flows.py
poppy/flows/jax/utils.py
poppy/flows/torch/__init__.py
poppy/flows/torch/flows.py
poppy/samplers/__init__.py
poppy/samplers/base.py
poppy/samplers/importance.py
poppy/samplers/mcmc.py
poppy/samplers/smc/__init__.py
poppy/samplers/smc/base.py
poppy/samplers/smc/emcee.py
poppy/samplers/smc/minipcn.py
poppy_inference-0.1.0a1.dist-info/licenses/LICENSE
poppy_inference-0.1.0a1.dist-info/METADATA
poppy_inference-0.1.0a1.dist-info/WHEEL
poppy_inference-0.1.0a1.dist-info/top_level.txt
poppy_inference-0.1.0a1.dist-info/RECORD
